<!-- $Id$ -->
<autobuild>
    <configuration>
        <variable name="name"      value="suse111_64_gcc" />
        <variable name="configs"  value="Linux Exceptions ZLIB SSL ZIOP" />
        <include name="buildenv.xml" />
    </configuration>

    <include name="preprocess.xml" />

    <command name="file_manipulation" options="type=create file=ACE/ace/config.h output='#define IDL_ANON_ERROR\n#define TAO_SUPPRESS_NEW_LINE_IN_EXCEPTION_LOGGING\n#include \x22ace/config-linux.h\x22\n'"/>
    <command name="file_manipulation" options="type=create file=ACE/include/makeinclude/platform_macros.GNU output='dds4ccm_ndds=1\nndds=1\nbuildbits=64\nzlib=1\nxerces3=1\ninclude $(ACE_ROOT)/include/makeinclude/platform_linux.GNU\n'" />
    <command name="file_manipulation" options="type=create file=ACE/bin/MakeProjectCreator/config/default.features output='dds4ccm_ndds=1\nndds=1\nzlib=1\nxerces3=1\n'" />

    <include name="printbuildenv.xml" />

    <command name="generate_workspace" options="-type gnuautobuild -exclude TAO,CIAO,DAnCE" />

    <command name="make"              options="-k" />

    <command name="auto_run_tests"    options="-a script_path=$ACE_ROOT/bin" />

    <include name="postprocess.xml" />
</autobuild>
